awesome_list_generator/__init__.py
awesome_list_generator/__init__.pyi
awesome_list_generator/py.typed
awesome_list_generator/cli/__init__.py
awesome_list_generator/cli/__init__.pyi
awesome_list_generator/cli/_app.py
awesome_list_generator/config/__init__.py
awesome_list_generator/config/__init__.pyi
awesome_list_generator/config/_category.py
awesome_list_generator/config/_config.py
awesome_list_generator/config/_configuration.py
awesome_list_generator/config/_project.py
awesome_list_generator/generator/__init__.py
awesome_list_generator/generator/__init__.pyi
awesome_list_generator/generator/formats/__init__.py
awesome_list_generator/generator/formats/__init__.pyi
awesome_list_generator/generator/formats/_base.py
awesome_list_generator/generator/formats/_enum.py
awesome_list_generator/generator/formats/markdown/__init__.py
awesome_list_generator/generator/formats/markdown/__init__.pyi
awesome_list_generator/generator/formats/markdown/_badge.py
awesome_list_generator/generator/formats/markdown/_markdown.py
awesome_list_generator/plugin/__init__.py
awesome_list_generator/plugin/__init__.pyi
awesome_list_generator/plugin/_github.py
awesome_list_generator/plugin/_info.py
awesome_list_generator-0.1.9.dist-info/METADATA
awesome_list_generator-0.1.9.dist-info/WHEEL
awesome_list_generator-0.1.9.dist-info/entry_points.txt
awesome_list_generator-0.1.9.dist-info/licenses/LICENSE
awesome_list_generator-0.1.9.dist-info/RECORD
