Metadata-Version: 2.4
Name: awesome-list-generator
Version: 0.1.9
Summary: 📚✨ Automate awesome lists with GitHub metadata & markdown magic!
Project-URL: Changelog, https://github.com/liblaf/awesome-list-generator/blob/main/CHANGELOG.md
Project-URL: Homepage, https://github.com/liblaf/awesome-list-generator
Project-URL: Issue Tracker, https://github.com/liblaf/awesome-list-generator/issues
Project-URL: Release Notes, https://github.com/liblaf/awesome-list-generator/releases
Project-URL: Source Code, https://github.com/liblaf/awesome-list-generator
Author-email: liblaf <30631553+liblaf@users.noreply.github.com>
License-Expression: MIT
License-File: LICENSE
Keywords: automation,awesome,cli,data-visualization,dependency-management,documentation,github-api,markdown,project-management,python
Classifier: Development Status :: 4 - Beta
Classifier: Environment :: Console
Classifier: Intended Audience :: Developers
Classifier: License :: OSI Approved :: MIT License
Classifier: Programming Language :: Python
Classifier: Programming Language :: Python :: 3.12
Classifier: Programming Language :: Python :: 3.13
Classifier: Topic :: Utilities
Classifier: Typing :: Typed
Requires-Python: <4,>=3.12
Requires-Dist: environs>=14.1.0
Requires-Dist: githubkit<0.13,>=0.12.5
Requires-Dist: lazy-loader<0.5,>=0.4
Requires-Dist: liblaf-grapes<0.1.14,>=0.1.13
Requires-Dist: loguru<0.8,>=0.7.3
Requires-Dist: pydantic<3,>=2.10.6
Requires-Dist: ruamel-yaml<0.19,>=0.18.10
Requires-Dist: typer<0.16,>=0.15.1
